shipyard_microsoft_onedrive/__init__.py
shipyard_microsoft_onedrive/cli/authtest.py
shipyard_microsoft_onedrive/cli/onedrive_download.py
shipyard_microsoft_onedrive/cli/onedrive_move.py
shipyard_microsoft_onedrive/cli/onedrive_remove.py
shipyard_microsoft_onedrive/cli/onedrive_upload.py
shipyard_microsoft_onedrive/drive_client.py
shipyard_microsoft_onedrive/utils.py
shipyard_microsoft_onedrive-0.2.0.dist-info/METADATA
shipyard_microsoft_onedrive-0.2.0.dist-info/WHEEL
shipyard_microsoft_onedrive-0.2.0.dist-info/RECORD
