Metadata-Version: 2.1
Name: shipyard-microsoft-onedrive
Version: 0.2.0
Summary: A local client for working with files in Microsoft OneDrive
Author: wrp801
Author-email: wespoulsen@gmail.com
Requires-Python: >=3.9,<4.0
Classifier: Programming Language :: Python :: 3
Classifier: Programming Language :: Python :: 3.9
Classifier: Programming Language :: Python :: 3.10
Classifier: Programming Language :: Python :: 3.11
Requires-Dist: msal (>=1.28.1,<2.0.0)
Requires-Dist: office365-rest-python-client (>=2.5.10,<3.0.0)
Requires-Dist: pandas (>=2.0,<3.0)
Requires-Dist: requests (==2.31)
Requires-Dist: shipyard-bp-utils (>=1.2.1,<2.0.0)
Requires-Dist: shipyard-templates (==0.9.0)
